ots_sdk/__init__.py
ots_sdk/api.py
ots_sdk/helpers.py
ots_sdk/http_client.py
ots_sdk/models.py
ots_sdk-1.0.0.dist-info/LICENSE
ots_sdk-1.0.0.dist-info/METADATA
ots_sdk-1.0.0.dist-info/WHEEL
ots_sdk-1.0.0.dist-info/RECORD
