Metadata-Version: 2.3
Name: ots-sdk
Version: 1.0.0
Summary: Forked Python SDK for the Omnia Timeseries API
Requires-Python: >=3.10,<4.0
Classifier: Programming Language :: Python :: 3
Classifier: Programming Language :: Python :: 3.10
Classifier: Programming Language :: Python :: 3.11
Classifier: Programming Language :: Python :: 3.12
Classifier: Programming Language :: Python :: 3.13
Requires-Dist: azure-core
Requires-Dist: azure-identity (>=1.24.0)
Requires-Dist: cryptography (>=43.0.3)
Requires-Dist: opentelemetry-api (>=1.27.0,<2.0.0)
Requires-Dist: opentelemetry-instrumentation-requests (>=0.48b0,<1.0.0)
Requires-Dist: requests (>=2.32.5,<3.0.0)
Project-URL: Repository, https://github.com/asmfstatoil/omnia-timeseries-python
